mathcrypto/__init__.py
mathcrypto/cryptography/__init__.py
mathcrypto/cryptography/diffie_hellman.py
mathcrypto/cryptography/elliptic_curves.py
mathcrypto/cryptography/primes.py
mathcrypto/math/__init__.py
mathcrypto/math/funcs.py
mathcrypto/math/groups.py
tests/__init__.py
tests/test_cryptography_primes.py
tests/test_math_funcs.py
tests/test_math_groups.py
mathcrypto-0.3.2.dist-info/LICENSE
mathcrypto-0.3.2.dist-info/METADATA
mathcrypto-0.3.2.dist-info/WHEEL
mathcrypto-0.3.2.dist-info/top_level.txt
mathcrypto-0.3.2.dist-info/RECORD
