Metadata-Version: 2.1
Name: mathcrypto
Version: 0.3.2
Summary: A library of useful funtions used in cryptography. For learning purposes only.
Home-page: https://github.com/Czechbol/mathcrypto
Author: Adam Ludes
Author-email: adam@ludes.cz
License: MIT
Project-URL: Bug Tracker, https://github.com/Czechbol/mathcrypto/issues
Keywords: mathematics,number_theory,prime_numbers,cryptography
Classifier: License :: OSI Approved :: MIT License
Classifier: Operating System :: OS Independent
Classifier: Programming Language :: Python
Classifier: Programming Language :: Python :: 3
Classifier: Programming Language :: Python :: 3.8
Classifier: Programming Language :: Python :: 3.9
Requires-Python: >=3.8
License-File: LICENSE
